metaflowx/__init__.py
metaflowx/cli_components/__init__.py
metaflowx/cli_components/dump_cmd.py
metaflowx/cli_components/init_cmd.py
metaflowx/cli_components/making_boosting.py
metaflowx/cli_components/making_decision_tree.py
metaflowx/cli_components/making_regression_tree.py
metaflowx/cli_components/making_svm.py
metaflowx/cli_components/run_cmds.py
metaflowx/cli_components/step_cmd.py
metaflowx/cli_components/utils.py
metaflowx/frozen/__init__.py
metaflowx/frozen/algo_bagging.py
metaflowx/frozen/ass_rule_mining.py
metaflowx/frozen/centroid_vs_medoid.py
metaflowx/frozen/challenges_in_ml.py
metaflowx/frozen/dbscan.py
metaflowx/frozen/dbscan_point_differences.py
metaflowx/frozen/dbscan_q.py
metaflowx/frozen/dbscan_t.py
metaflowx/frozen/diff_bag_boost.py
metaflowx/frozen/diff_paas_iaas_saas.py
metaflowx/frozen/diff_super_unsper.py
metaflowx/frozen/gcp.py
metaflowx/frozen/gd_convergence.py
metaflowx/frozen/gen_svm.py
metaflowx/frozen/gradient_descent.py
metaflowx/frozen/hac.py
metaflowx/frozen/hac_q.py
metaflowx/frozen/hybrid_cloud.py
metaflowx/frozen/iaas.py
metaflowx/frozen/ica.py
metaflowx/frozen/imbalanced_classification.py
metaflowx/frozen/kfoldcv.py
metaflowx/frozen/knn.py
metaflowx/frozen/limit_bagging.py
metaflowx/frozen/limit_tree.py
metaflowx/frozen/map_reduce_lambda.py
metaflowx/frozen/maximal_margin_classifier.py
metaflowx/frozen/ml_classification.py
metaflowx/frozen/negentropy.py
metaflowx/frozen/paas.py
metaflowx/frozen/private_cloud.py
metaflowx/frozen/public_cloud.py
metaflowx/frozen/resampling_methods.py
metaflowx/frozen/saas.py
metaflowx/frozen/threshold_precision_recall.py
metaflowx/optimiser/__init__.py
metaflowx/optimiser/adv_reg/__init__.py
metaflowx/optimiser/adv_reg/bin_smoother.py
metaflowx/optimiser/adv_reg/gam.py
metaflowx/optimiser/adv_reg/kernel_smoother.py
metaflowx/optimiser/adv_reg/knn_smoother.py
metaflowx/optimiser/adv_reg/lowess.py
metaflowx/optimiser/adv_reg/lwr.py
metaflowx/optimiser/adv_reg/spline_fit.py
metaflowx-1.1.10.dist-info/licenses/LICENSE
metaflowx-1.1.10.dist-info/METADATA
metaflowx-1.1.10.dist-info/WHEEL
metaflowx-1.1.10.dist-info/top_level.txt
metaflowx-1.1.10.dist-info/RECORD
