Metadata-Version: 2.4
Name: metaflowx
Version: 1.1.10
Summary: A comprehensive, modular machine-learning framework that consolidates datasets, model architectures, optimization algorithms, preprocessing utilities, and evaluation tools into a unified toolkit designed for research, experimentation, and education. metaflowx streamlines end-to-end workflows—from data ingestion to model selection, training, tuning, and validation—empowering learners and researchers with a clean, extensible, and production-aware interface.
Author: Suchana Chakraborty
Author-email: metaflowx <the.application.in@gmail.com>
License: MIT License
Keywords: machine-learning,classification,regression,data-science,automated-ml
Requires-Python: >=3.7
License-File: LICENSE
Requires-Dist: numpy<3.0,>=1.23
Requires-Dist: pandas>=1.5
Requires-Dist: scikit-learn>=1.2
Requires-Dist: matplotlib>=3.7
Requires-Dist: seaborn>=0.12
Requires-Dist: plotly>=5.0
Requires-Dist: tqdm
Requires-Dist: autograd
Dynamic: author
Dynamic: license-file
Dynamic: requires-python
